brawl_api/__init__.py
brawl_api/core.py
brawl_api/models.py
brawl_api/utils.py
brawl_api-0.0.1a4.dist-info/LICENSE
brawl_api-0.0.1a4.dist-info/WHEEL
brawl_api-0.0.1a4.dist-info/METADATA
brawl_api-0.0.1a4.dist-info/RECORD
